{"app": "bolao-copa-2026", "version": 1, "exportedAt": 1783936476089, "meta": {"shareUrl": "https://sweet-vacherin-c8f912.netlify.app/", "scoring": {"exact": 25, "winner": 12, "diff": 18}, "aposta": {"taxaOrg": 20, "pix": {"tipo": "E-mail", "nome": "ABMAEL GOMES NETO", "chave": "abmaelgomesneto@hotmail.com", "cidade": "GRAJAÚ"}, "premios": [100], "valor": 50}, "nome": "BOLÃO ENTRE AMIGOS - GRAJAÚ/MA", "pin": "171299PpAbm"}, "matches": [{"teamB": "Noruega", "live": false, "teamA": "Brasil", "dateISO": "2026-07-05T17:00", "scoreB": 2, "phase": "Oitavas", "id": "mr6culpdmztrdk", "scoreA": 1}, {"live": false, "teamB": "Inglaterra", "teamA": "México", "scoreB": 3, "dateISO": "2026-07-05T21:00", "id": "mr6cvlfwz0yow0", "scoreA": 2, "phase": "Oitavas"}], "participants": [{"id": "mr21kk672o1kz1", "fone": "99991213209", "codeHash": "a28ca4", "nome": "Abmael Neto", "pago": true, "comprovante": null, "obs": "", "predictions": {"mr6cvlfwz0yow0": {"b": 0, "a": 1}, "mr6culpdmztrdk": {"b": 1, "a": 2}}}, {"id": "mr21pbk86gn849", "fone": "99991378376", "codeHash": "i4xr2z", "nome": "Neto", "pago": false, "comprovante": null, "obs": "", "predictions": {}}, {"fone": "98984123775", "id": "mr227hp0ybxwet", "codeHash": "1v5gt7u", "nome": "Sandynes", "pago": false, "comprovante": null, "predictions": {}, "obs": ""}, {"comprovante": null, "nome": "Marcia Cristina da Conceição lopes", "pago": true, "predictions": {"mr6cvlfwz0yow0": {"b": 2, "a": 1}, "mr6culpdmztrdk": {"b": 0, "a": 1}}, "obs": "", "fone": "99991856174", "id": "mr22g6rlt4wvio", "codeHash": "hgbkd5"}, {"codeHash": "1usrghj", "id": "mr22tdnm7a9bk3", "fone": "98984093416", "predictions": {}, "pago": false, "nome": "Silvan", "comprovante": null}, {"obs": "", "predictions": {}, "pago": false, "nome": "Alexandre bi", "comprovante": null, "codeHash": "1wvcgi0", "fone": "99981080405", "id": "mr22y2lgj4anhg"}, {"nome": "Fátima Barros", "pago": false, "comprovante": null, "obs": "", "predictions": {}, "fone": "99991562454", "id": "mr23i86ssphjog", "codeHash": "1yess1p"}, {"obs": "", "predictions": {}, "pago": false, "nome": "Raimundo Pereira", "comprovante": null, "codeHash": "1yess1p", "id": "mr25qpg8i8h6cg", "fone": "99984056375"}, {"obs": "", "predictions": {}, "pago": false, "nome": "Pedro Vinicius", "comprovante": null, "codeHash": "10rex5b", "id": "mr29a796ep1prf", "fone": "99991619806"}, {"codeHash": "161545n", "id": "mr2bf63o3elrsd", "fone": "99984691384", "predictions": {}, "obs": "", "comprovante": null, "nome": "Arnaldinho", "pago": false}, {"id": "mr54rqfsez1ba2", "fone": "91991458898", "codeHash": "1ysg619", "nome": "Breno Milhomem", "pago": false, "comprovante": null, "predictions": {}}, {"predictions": {}, "pago": false, "nome": "Daniel Neto", "comprovante": null, "codeHash": "q1qugk", "id": "mr55jiypexfc0b", "fone": "99991913370"}, {"codeHash": "d8dnph", "fone": "99992097655", "id": "mr570hpnq5bvon", "predictions": {"mr6cvlfwz0yow0": {"a": 2, "b": 1}, "mr6culpdmztrdk": {"b": 1, "a": 3}}, "obs": "", "pago": true, "nome": "Admiel Neto", "comprovante": {"tipo": "img", "ts": 1783247774998}}, {"fone": "98984687653", "id": "mr57ri2m30zbkf", "codeHash": "1yess1p", "nome": "Valderiza Barros", "pago": false, "comprovante": null, "predictions": {}}, {"codeHash": "1jtjsz0", "id": "mr5a4rzbxfkl57", "fone": "99991710649", "predictions": {}, "comprovante": null, "pago": false, "nome": "Thales"}, {"predictions": {"mr6culpdmztrdk": {"a": 2, "b": 0}, "mr6cvlfwz0yow0": {"a": 1, "b": 1}}, "obs": "", "comprovante": {"ts": 1783266925923, "tipo": "pdf"}, "nome": "Daniel Neto", "pago": true, "codeHash": "q1qugk", "fone": "99991913370", "id": "mr7yyit2ndkp3y"}, {"codeHash": "3zgr7n", "id": "mr7zel6nol48ov", "fone": "99991233433", "predictions": {"mr6culpdmztrdk": {"a": 3, "b": 0}, "mr6cvlfwz0yow0": {"a": 2, "b": 1}}, "obs": "", "nome": "Helio Carvalho", "pago": true}, {"nome": "Maria de Fátima Barros", "pago": true, "predictions": {"mr6culpdmztrdk": {"b": 2, "a": 3}, "mr6cvlfwz0yow0": {"a": 1, "b": 2}}, "obs": "", "fone": "99991562454", "id": "mr811l5xpw91wa", "codeHash": "1yess1p"}], "receipts": {}}